setup.cfg
setup.py
pyhelper/TimeProfiler.py
pyhelper/__init__.py
pyhelper/dataframeutils.py
pyhelper/datetimeutils.py
pyhelper/decorator.py
pyhelper/fileutils.py
pyhelper.egg-info/PKG-INFO
pyhelper.egg-info/SOURCES.txt
pyhelper.egg-info/dependency_links.txt
pyhelper.egg-info/requires.txt
pyhelper.egg-info/top_level.txt