Metadata-Version: 1.1
Name: pyhelper
Version: 0.0.0
Summary: A collection of useful python utilities
Home-page: https://github.com/caviler/pyhelper
Author: caviler
Author-email: caviler@gmail.com
License: BSD
Keywords: pyhelper python utilities thread lock cache
Platform: UNKNOWN
Classifier: Development Status :: 3 - Alpha
Classifier: Programming Language :: Python :: 2.7
Classifier: Programming Language :: Python :: 3.4
Classifier: Programming Language :: Python :: 3.5
Classifier: License :: OSI Approved :: BSD License
